cdef_parquet_scanner/__init__.py
cdef_parquet_scanner/schema.py
cdef_parquet_scanner-0.1.0.dist-info/METADATA
cdef_parquet_scanner-0.1.0.dist-info/WHEEL
cdef_parquet_scanner-0.1.0.dist-info/entry_points.txt
cdef_parquet_scanner-0.1.0.dist-info/licenses/LICENSE
cdef_parquet_scanner-0.1.0.dist-info/RECORD
