Metadata-Version: 2.4
Name: cdef-parquet-scanner
Version: 0.1.0
Summary: Tool for scanning and analyzing Parquet schema structures
Project-URL: Homepage, https://github.com/tkragholm/cdef-parquet-scanner
Project-URL: Bug Tracker, https://github.com/tkragholm/cdef-parquet-scanner/issues
Author-email: Tobias Kragholm <tkragholm@gmail.com>
License-File: LICENSE
Classifier: License :: OSI Approved :: MIT License
Classifier: Operating System :: OS Independent
Classifier: Programming Language :: Python :: 3
Requires-Python: >=3.8
Requires-Dist: pyarrow>=10.0.0
